signal_ocean/__init__.py
signal_ocean/_internals.py
signal_ocean/connection.py
signal_ocean/plots.py
signal_ocean/port.py
signal_ocean/port_api.py
signal_ocean/port_filter.py
signal_ocean/vessel_class.py
signal_ocean/vessel_class_api.py
signal_ocean/vessel_class_filter.py
signal_ocean/companies/__init__.py
signal_ocean/companies/companies_api.py
signal_ocean/companies/models.py
signal_ocean/distances/__init__.py
signal_ocean/distances/_distances_json.py
signal_ocean/distances/distances_api.py
signal_ocean/distances/loading_condition.py
signal_ocean/distances/models.py
signal_ocean/distances/port.py
signal_ocean/distances/port_filter.py
signal_ocean/distances/vessel_class.py
signal_ocean/distances/vessel_class_filter.py
signal_ocean/freight_pricing/__init__.py
signal_ocean/freight_pricing/_freight_pricing_json.py
signal_ocean/freight_pricing/freight_pricing_api.py
signal_ocean/freight_pricing/models.py
signal_ocean/freight_pricing/port.py
signal_ocean/freight_pricing/port_filter.py
signal_ocean/freight_pricing/vessel_class.py
signal_ocean/freight_pricing/vessel_class_filter.py
signal_ocean/freight_pricing/vessel_subclass.py
signal_ocean/freight_pricing/vessel_type.py
signal_ocean/freight_pricing/vessel_type_filter.py
signal_ocean/freight_rates/__init__.py
signal_ocean/freight_rates/_freight_rates_json.py
signal_ocean/freight_rates/enums.py
signal_ocean/freight_rates/freight_rates_api.py
signal_ocean/freight_rates/models.py
signal_ocean/freight_rates/port_filter.py
signal_ocean/freight_rates/utils.py
signal_ocean/geos/__init__.py
signal_ocean/geos/geos_api.py
signal_ocean/geos/models.py
signal_ocean/historical_tonnage_list/__init__.py
signal_ocean/historical_tonnage_list/_historical_tonnage_list_json.py
signal_ocean/historical_tonnage_list/area.py
signal_ocean/historical_tonnage_list/column.py
signal_ocean/historical_tonnage_list/commercial_status.py
signal_ocean/historical_tonnage_list/fixture_type.py
signal_ocean/historical_tonnage_list/historical_tonnage_list.py
signal_ocean-13.7.0.dist-info/LICENSE
signal_ocean-13.7.0.dist-info/METADATA
signal_ocean-13.7.0.dist-info/WHEEL
signal_ocean-13.7.0.dist-info/top_level.txt
signal_ocean-13.7.0.dist-info/RECORD
