Metadata-Version: 2.1
Name: signal-ocean
Version: 13.7.0
Summary: Access Signal Ocean Platform data using Python.
Home-page: https://apis.signalocean.com/
Author: Signal Ocean Developers
Author-email: signaloceandevelopers@thesignalgroup.com
License: Apache 2.0
Project-URL: The Signal Group, https://www.thesignalgroup.com/
Project-URL: Signal Ocean, https://www.signalocean.com/
Project-URL: The Signal Ocean Platform, https://app.signalocean.com
Platform: UNKNOWN
Classifier: Development Status :: 4 - Beta
Classifier: Programming Language :: Python :: 3.7
Classifier: Programming Language :: Python :: 3.8
Classifier: Programming Language :: Python :: 3.9
Classifier: License :: OSI Approved :: Apache Software License
Requires-Python: >=3.7
Requires-Dist: requests (<3,>=2.23.0)
Requires-Dist: python-dateutil (<3,>=2.8.1)
Requires-Dist: pandas (<3,>=1.0.3)
Requires-Dist: numpy (>=1.18.5)
Requires-Dist: strictly-typed-pandas (==0.1.4)
Requires-Dist: typeguard (<3.0.0,>=2.13.3)
